komiker/__init__.py
komiker/data.json
komiker/ex.py
komiker/generate.py
komiker/komik.py
komiker/update.json
komiker/data/bk.json
komiker/data/bs.json
komiker/data/dd.json
komiker/data/ka.json
komiker/data/kb.json
komiker/data/kc.json
komiker/data/kg.json
komiker/data/ki.json
komiker/data/kk.json
komiker/data/kl.json
komiker/data/km.json
komiker/data/kn.json
komiker/data/ks.json
komiker/data/kt.json
komiker/data/ky.json
komiker/data/kz.json
komiker/data/mb.json
komiker/data/mc.json
komiker/data/md.json
komiker/data/mg.json
komiker/data/mi.json
komiker/data/mk.json
komiker/data/mo.json
komiker/data/mp.json
komiker/data/ms.json
komiker/data/mt.json
komiker/data/mw.json
komiker/data/ng.json
komiker/data/pm.json
komiker/data/sd.json
komiker/data/si.json
komiker/data/sk.json
komiker/data/wm.json
komiker-1.0.9.dist-info/LICENSE
komiker-1.0.9.dist-info/METADATA
komiker-1.0.9.dist-info/WHEEL
komiker-1.0.9.dist-info/top_level.txt
komiker-1.0.9.dist-info/RECORD
