Metadata-Version: 2.1
Name: komiker
Version: 1.0.9
Summary: Tutorial komiker-py: https://m.youtube.com/watch?v=wmlFLnWmaa0
Home-page: https://github.com/komiker-py
Author: pemula
Maintainer: pemula
License: Dilindungi oleh Raja Iblis Merlin Lucifer.
Download-URL: https://m.youtube.com/watch?v=wmlFLnWmaa0
Keywords: komiker,komik,downloader
Platform: Any
Classifier: Development Status :: 5 - Production/Stable
Classifier: Intended Audience :: Developers
Classifier: License :: Free for non-commercial use
Classifier: Natural Language :: Indonesian
Classifier: Operating System :: OS Independent
Classifier: Operating System :: Android
Classifier: Topic :: Software Development :: Libraries :: Python Modules
Classifier: Topic :: Internet
Classifier: Programming Language :: Python :: 3.4
Classifier: Programming Language :: Python :: 3.5
Classifier: Programming Language :: Python :: 3.6
Classifier: Programming Language :: Python :: 3.7
Classifier: Programming Language :: Python :: 3.8
Classifier: Programming Language :: Python :: 3.9
Requires-Dist: pip (>=21.0.1)
Requires-Dist: tqdm (==4.56.0)
Requires-Dist: fake-headers (==1.0.2)
Requires-Dist: aiohttp (==3.7.3)
Requires-Dist: requests (==2.25.1)
Requires-Dist: pycrypto (==2.6.1)
Requires-Dist: backports.pbkdf2 (==0.1)
